datahub_core/__init__.py
datahub_core/analyse.py
datahub_core/metrics.py
datahub_core/printable.py
datahub_core/data/__init__.py
datahub_core/data/codes.txt
datahub_core/data/company_names.txt
datahub_core/data/country-codes.txt
datahub_core/data/data_access.py
datahub_core/data/sic-codes.txt
datahub_core/data/sic-conventions.json
datahub_core/data/sic-ranges.txt
datahub_core/data/__pycache__/__init__.cpython-38.pyc
datahub_core/data/__pycache__/data_access.cpython-38.pyc
datahub_core/data/addresses/US.json
datahub_core/data/addresses/__init__.py
datahub_core/data/funds/__init__.py
datahub_core/data/funds/asset_class.csv
datahub_core/data/funds/classes.csv
datahub_core/data/funds/dividend_treatment.csv
datahub_core/data/funds/regions.csv
datahub_core/datasets/__init__.py
datahub_core/datasets/address.py
datahub_core/datasets/country.py
datahub_core/datasets/lei.py
datahub_core/datasets/person.py
datahub_core/datasets/sic_code.py
datahub_core/datasets/sic_range.py
datahub_core/generators/__init__.py
datahub_core/generators/context.py
datahub_core/generators/counter_state.py
datahub_core/generators/generate.py
datahub_core/generators/object_decorators.py
datahub_core/generators/results_object.py
datahub_core/generators/attribute_generators/__init__.py
datahub_core/generators/attribute_generators/address_generator.py
datahub_core/generators/attribute_generators/choice_generator.py
datahub_core/generators/attribute_generators/company_name_faker.py
datahub_core/generators/attribute_generators/company_name_markov.py
datahub_core/generators/attribute_generators/company_name_suffix.py
datahub_core/generators/attribute_generators/country_code_generator.py
datahub_core/generators/attribute_generators/fund_name_generator.py
datahub_core/generators/attribute_generators/legal_entity_name_generator2.py
datahub_core/generators/attribute_generators/lei_generator.py
datahub_core/generators/attribute_generators/normal_generator.py
datahub_core_grovesy-0.9.10.dist-info/LICENSE
datahub_core_grovesy-0.9.10.dist-info/LICENSE.spdx
datahub_core_grovesy-0.9.10.dist-info/METADATA
datahub_core_grovesy-0.9.10.dist-info/NOTICE
datahub_core_grovesy-0.9.10.dist-info/WHEEL
datahub_core_grovesy-0.9.10.dist-info/top_level.txt
datahub_core_grovesy-0.9.10.dist-info/zip-safe
datahub_core_grovesy-0.9.10.dist-info/RECORD
