Metadata-Version: 2.1
Name: datahub-core-grovesy
Version: 0.9.10
Summary: Synthetic data generation tools for financial markets
Home-page: https://github.com/finos/datahub
Author: grovesy
Author-email: paul.groves@citi.com
License: UNKNOWN
Platform: UNKNOWN
